m6rclib/__init__.py
m6rclib/embed_lexer.py
m6rclib/metaphor_ast_node.py
m6rclib/metaphor_formatters.py
m6rclib/metaphor_lexer.py
m6rclib/metaphor_parser.py
m6rclib/metaphor_token.py
m6rclib-0.6.1.dist-info/METADATA
m6rclib-0.6.1.dist-info/WHEEL
m6rclib-0.6.1.dist-info/licenses/LICENSE.txt
m6rclib-0.6.1.dist-info/RECORD
