Metadata-Version: 2.4
Name: m6rclib
Version: 0.6.1
Summary: An embedded parser and LLM AI prompt compiler for the Metaphor language
Project-URL: Homepage, https://github.com/m6r-ai/m6rclib
Project-URL: Bug Tracker, https://github.com/m6r-ai/m6rclib/issues
Project-URL: Repository, https://github.com/m6r-ai/m6rclib.git
Author-email: Dave Hudson <dave@m6r.ai>
License: 
License-File: LICENSE.txt
Keywords: ai,metaphor,prompt-compiler
Classifier: Development Status :: 3 - Alpha
Classifier: Environment :: Console
Classifier: Intended Audience :: Developers
Classifier: License :: OSI Approved :: Apache Software License
Classifier: Operating System :: OS Independent
Classifier: Programming Language :: Python :: 3
Classifier: Programming Language :: Python :: 3.8
Classifier: Programming Language :: Python :: 3.9
Classifier: Programming Language :: Python :: 3.10
Classifier: Programming Language :: Python :: 3.11
Classifier: Programming Language :: Python :: 3.12
Classifier: Programming Language :: Python :: 3.13
Classifier: Topic :: Software Development :: Libraries :: Python Modules
Requires-Python: >=3.8
Provides-Extra: dev
Requires-Dist: pytest-cov>=4.0; extra == 'dev'
Requires-Dist: pytest>=7.0; extra == 'dev'
